lucheng_models/__init__.py
lucheng_models/contract_record.py
lucheng_models/health_record.py
lucheng_models/patient_registration.py
lucheng_models-2025.9.19.2.dist-info/METADATA
lucheng_models-2025.9.19.2.dist-info/WHEEL
lucheng_models-2025.9.19.2.dist-info/licenses/LICENSE
lucheng_models-2025.9.19.2.dist-info/RECORD
